hx3/__init__.py
hx3/api.py
hx3-0.2.1.dist-info/licenses/LICENSE.md
hx3-0.2.1.dist-info/METADATA
hx3-0.2.1.dist-info/WHEEL
hx3-0.2.1.dist-info/top_level.txt
hx3-0.2.1.dist-info/RECORD
