Metadata-Version: 2.4
Name: hx3
Version: 0.2.1
Summary: Hx 3 API
Home-page: https://github.com/jaredhobbs/hx3
Author: Jared Hobbs
Author-email: jared@pyhacker.com
Project-URL: Bug Reports, https://github.com/jaredhobbs/hx3/issues
Requires-Python: >=3.6
License-File: LICENSE.md
Requires-Dist: gql==2.0.0
Dynamic: author
Dynamic: author-email
Dynamic: description
Dynamic: description-content-type
Dynamic: home-page
Dynamic: license-file
Dynamic: project-url
Dynamic: requires-dist
Dynamic: requires-python
Dynamic: summary
